MysqlWebApp/MysqlApplication.py
MysqlWebApp/__init__.py
MysqlWebApp/templates/config_mysql.html
MysqlWebApp/templates/home.html
MysqlWebApp-1.3.1.dist-info/LICENSE.txt
MysqlWebApp-1.3.1.dist-info/METADATA
MysqlWebApp-1.3.1.dist-info/WHEEL
MysqlWebApp-1.3.1.dist-info/top_level.txt
MysqlWebApp-1.3.1.dist-info/RECORD
