Metadata-Version: 2.2
Name: MysqlWebApp
Version: 1.3.1
Summary: A Python package for building dynamic MySQL-powered web applications with template support
Home-page: https://github.com/abuawaish/Crud_app
Author: Abu Awaish
Author-email: abuawaish7@gmail.com
License: MIT
Keywords: web application flask mysql dynamic templates
Classifier: Programming Language :: Python :: 3
Classifier: License :: OSI Approved :: MIT License
Classifier: Operating System :: OS Independent
Requires-Python: >=3.6
License-File: LICENSE.txt
Requires-Dist: Flask
Requires-Dist: Flask-MySQLdb
Dynamic: author
Dynamic: author-email
Dynamic: classifier
Dynamic: description
Dynamic: description-content-type
Dynamic: home-page
Dynamic: keywords
Dynamic: license
Dynamic: requires-dist
Dynamic: requires-python
Dynamic: summary
